pyuploadcare/__init__.py
pyuploadcare/api/__init__.py
pyuploadcare/api/addon_entities.py
pyuploadcare/api/api.py
pyuploadcare/api/auth.py
pyuploadcare/api/base.py
pyuploadcare/api/client.py
pyuploadcare/api/entities.py
pyuploadcare/api/metadata.py
pyuploadcare/api/responses.py
pyuploadcare/api/utils.py
pyuploadcare/client.py
pyuploadcare/conf.py
pyuploadcare/dj/__init__.py
pyuploadcare/dj/client.py
pyuploadcare/dj/conf.py
pyuploadcare/dj/forms.py
pyuploadcare/dj/models.py
pyuploadcare/dj/static/uploadcare/blocks.min.js
pyuploadcare/dj/static/uploadcare/lr-file-uploader-inline.min.css
pyuploadcare/dj/static/uploadcare/lr-file-uploader-minimal.min.css
pyuploadcare/dj/static/uploadcare/lr-file-uploader-regular.min.css
pyuploadcare/dj/static/uploadcare/uploadcare.full.min.js
pyuploadcare/dj/static/uploadcare/uploadcare.min.js
pyuploadcare/dj/subclassing.py
pyuploadcare/dj/templates/uploadcare/forms/widgets/file.html
pyuploadcare/exceptions.py
pyuploadcare/helpers.py
pyuploadcare/resources/__init__.py
pyuploadcare/resources/base.py
pyuploadcare/resources/file.py
pyuploadcare/resources/file_group.py
pyuploadcare/resources/file_list.py
pyuploadcare/resources/group_list.py
pyuploadcare/resources/utils.py
pyuploadcare/secure_url.py
pyuploadcare/transformations/__init__.py
pyuploadcare/transformations/base.py
pyuploadcare/transformations/document.py
pyuploadcare/transformations/image.py
pyuploadcare/transformations/video.py
pyuploadcare/ucare_cli/__init__.py
pyuploadcare/ucare_cli/commands/__init__.py
pyuploadcare/ucare_cli/commands/convert_document.py
pyuploadcare/ucare_cli/commands/convert_video.py
pyuploadcare/ucare_cli/commands/create_group.py
pyuploadcare/ucare_cli/commands/create_webhook.py
pyuploadcare/ucare_cli/commands/delete_files.py
pyuploadcare/ucare_cli/commands/delete_webhook.py
pyuploadcare/ucare_cli/commands/get_file.py
pyuploadcare/ucare_cli/commands/get_project.py
pyuploadcare/ucare_cli/commands/helpers.py
pyuploadcare/ucare_cli/commands/list_files.py
pyuploadcare-5.1.0.dist-info/LICENSE
pyuploadcare-5.1.0.dist-info/METADATA
pyuploadcare-5.1.0.dist-info/WHEEL
pyuploadcare-5.1.0.dist-info/entry_points.txt
pyuploadcare-5.1.0.dist-info/RECORD
