Metadata-Version: 2.1
Name: pyuploadcare
Version: 5.1.0
Summary: Python library for Uploadcare.com
Home-page: https://uploadcare.com
Author: Uploadcare Inc
Author-email: hello@uploadcare.com
Requires-Python: >=3.8.1,<4.0.0
Classifier: Development Status :: 5 - Production/Stable
Classifier: Intended Audience :: Developers
Classifier: License :: OSI Approved :: MIT License
Classifier: Programming Language :: Python
Classifier: Programming Language :: Python :: 3
Classifier: Programming Language :: Python :: 3.9
Classifier: Programming Language :: Python :: 3.10
Classifier: Programming Language :: Python :: 3.11
Classifier: Programming Language :: Python :: 3.12
Classifier: Programming Language :: Python :: 3.8
Provides-Extra: django
Requires-Dist: Django (>=2.2) ; extra == "django"
Requires-Dist: httpx (>=0.25.1,<0.26.0)
Requires-Dist: pydantic[email] (>=2.5.2,<3.0.0)
Requires-Dist: python-dateutil (>=2.8.2,<3.0.0)
Requires-Dist: pytz (>=2023.3.post1,<2024.0)
Requires-Dist: typing-extensions (>=4.9.0,<5.0.0)
Project-URL: Bug Tracker, https://github.com/uploadcare/pyuploadcare/issues
Project-URL: Repository, https://github.com/uploadcare/pyuploadcare
